engine_antiantilopa/__init__.py
engine_antiantilopa/animation.py
engine_antiantilopa/camera.py
engine_antiantilopa/color.py
engine_antiantilopa/engine.py
engine_antiantilopa/entry.py
engine_antiantilopa/game_object.py
engine_antiantilopa/key_bind.py
engine_antiantilopa/label.py
engine_antiantilopa/on_click.py
engine_antiantilopa/scene.py
engine_antiantilopa/shape.py
engine_antiantilopa/sprite.py
engine_antiantilopa/surface.py
engine_antiantilopa/transform.py
engine_antiantilopa/vmath_mini.py
primitive_engine_antiantilopa-0.1.4.dist-info/licenses/LICENSE
primitive_engine_antiantilopa-0.1.4.dist-info/METADATA
primitive_engine_antiantilopa-0.1.4.dist-info/WHEEL
primitive_engine_antiantilopa-0.1.4.dist-info/top_level.txt
primitive_engine_antiantilopa-0.1.4.dist-info/RECORD
