Metadata-Version: 2.4
Name: primitive-engine-antiantilopa
Version: 0.1.4
Summary: A primitive engine to simplify work with pygame
Author-email: antiantilopa <santakamenb@qmail.com>
Classifier: Programming Language :: Python :: 3
Classifier: Operating System :: OS Independent
Classifier: License :: OSI Approved :: MIT License
Requires-Python: >=3.10
License-File: LICENSE
Dynamic: license-file
